genreml/__init__.py
genreml/fma_data/000002.mp3
genreml/fma_data/000005.mp3
genreml/fma_data/000010.mp3
genreml/fma_data/000140.mp3
genreml/fma_data/001039.mp3
genreml/fma_data/001040.mp3
genreml/fma_data/001066.mp3
genreml/fma_data/001069.mp3
genreml/fma_data/001073.mp3
genreml/fma_data/001075.mp3
genreml/fma_data/001082.mp3
genreml/fma_data/001083.mp3
genreml/model/__init__.py
genreml/model/__main__.py
genreml/model/acquisition/__init__.py
genreml/model/acquisition/config.py
genreml/model/acquisition/extraction.py
genreml/model/acquisition/request.py
genreml/model/acquisition/youtube.py
genreml/model/cnn/__init__.py
genreml/model/cnn/cnn.py
genreml/model/cnn/config.py
genreml/model/cnn/dataset.py
genreml/model/cnn/utils.py
genreml/model/cnn/data/feature_cols.csv
genreml/model/cnn/data/labels_key.csv
genreml/model/cnn/data/std_scaler_B.pkl
genreml/model/model/__init__.py
genreml/model/model/base_model.py
genreml/model/model/input.py
genreml/model/processing/__init__.py
genreml/model/processing/audio.py
genreml/model/processing/audio_features.py
genreml/model/processing/config.py
genreml/model/processing/display.py
genreml/model/utils/__init__.py
genreml/model/utils/file_handling.py
genreml/model/utils/logger.py
genreml/model/utils/model_utils.py
genreml/model/utils/multithreading.py
genreml/model/utils/string_parsing.py
genreml/model_resources/feature_cols.csv
genreml/model_resources/labels_key.csv
webapp/__init__.py
webapp/frontend/__init__.py
webapp/frontend/views.py
webapp/frontend/processing/__init__.py
webapp/frontend/processing/downloader.py
webapp/frontend/processing/feature_extraction.py
webapp/frontend/processing/genre_prediction.py
genreml-0.3.7.dist-info/LICENSE
genreml-0.3.7.dist-info/METADATA
genreml-0.3.7.dist-info/WHEEL
genreml-0.3.7.dist-info/entry_points.txt
genreml-0.3.7.dist-info/top_level.txt
genreml-0.3.7.dist-info/RECORD
