Metadata-Version: 2.1
Name: genreml
Version: 0.3.7
Summary: Data extraction and processing for genre prediction using ML
Home-page: https://github.com/adaros92/CS467-Project
License: MIT
Platform: UNKNOWN
Classifier: License :: OSI Approved :: MIT License
Classifier: Programming Language :: Python :: 3
Classifier: Programming Language :: Python :: 3.7
Requires-Python: >=3.5
Requires-Dist: librosa
Requires-Dist: matplotlib
Requires-Dist: numpy
Requires-Dist: pandas
Requires-Dist: pydub
Requires-Dist: requests
Requires-Dist: scikit-learn (==0.22.2.post1)
Requires-Dist: tabulate
Requires-Dist: tensorflow
Requires-Dist: youtube-dl
